zeushell/__init__.py
zeushell-1.0.2.dist-info/METADATA
zeushell-1.0.2.dist-info/WHEEL
zeushell-1.0.2.dist-info/top_level.txt
zeushell-1.0.2.dist-info/RECORD
