Metadata-Version: 2.1
Name: zeushell
Version: 1.0.2
Summary: A small Python package published to PyPI
Author-email: Zeus <zeus@gmail.com>
License: MIT
Keywords: example,package,pypi
Requires-Python: >=3.8
